{
  "code": "N20001644",
  "name": "Causeway_K4",
  "comment": "This JSON includes data for the area explorer app.",
  "type": "dz",
  "count": 3780,
  "parents": [
    {
      "code": "N21000377",
      "name": "Causeway_K",
      "type": "sdz"
    },
    {
      "code": "N10000404",
      "name": "Causeway",
      "type": "dea"
    },
    {
      "code": "N09000004",
      "name": "Causeway Coast and Glens",
      "type": "lgd"
    },
    {
      "code": "N92000002",
      "name": "Northern Ireland",
      "type": "ctry"
    }
  ],
  "children": [],
  "bounds": [
    [-6.5476, 55.1053],
    [-6.604, 55.1396]
  ],
  "data": {
    "population": {
      "perc": {
        "2011": {
          "all": 100
        },
        "2021": {
          "all": 100
        }
      },
      "value": {
        "2011": {
          "all": 0
        },
        "change": {
          "all": "Inf"
        },
        "2021": {
          "all": 717
        }
      },
      "value_rank": {
        "2011": {
          "all": 0
        },
        "2021": {
          "all": 295
        }
      }
    },
    "households": {
      "perc": {
        "2011": {
          "all_households": 100
        },
        "2021": {
          "all_households": 100
        }
      },
      "value": {
        "2011": {
          "all_households": 0
        },
        "change": {
          "all_households": "Inf"
        },
        "2021": {
          "all_households": 284
        }
      }
    },
    "cob": {
      "perc": {
        "2011": {
          "england": 100,
          "northern_ireland": 100,
          "other_cob": 100,
          "republic_of_ireland": 100,
          "scotland": 100,
          "wales": 100
        },
        "2021": {
          "england": 3.3333,
          "northern_ireland": 92.9167,
          "other_cob": 2.0833,
          "republic_of_ireland": 0.1389,
          "scotland": 1.5278,
          "wales": 0
        }
      }
    },
    "general_health": {
      "perc": {
        "2011": {
          "bad": 100,
          "fair": 100,
          "good": 100,
          "very_bad": 100,
          "very_good": 100
        },
        "2021": {
          "bad": 4.8815,
          "fair": 13.3891,
          "good": 28.7308,
          "very_bad": 1.2552,
          "very_good": 51.7434
        }
      }
    },
    "hh_size": {
      "perc": {
        "2011": {
          "five_people": 100,
          "four_people": 100,
          "one_person": 100,
          "three_people": 100,
          "two_people": 100
        },
        "2021": {
          "five_people": 7.3944,
          "four_people": 16.5493,
          "one_person": 23.2394,
          "three_people": 17.2535,
          "two_people": 35.5634
        }
      }
    },
    "highest_level_of_qualifications": {
      "perc": {
        "2011": {
          "apprenticeship": 100,
          "level_1_qualifications": 100,
          "level_2_qualifications": 100,
          "level_3_qualifications": 100,
          "level_4_qualifications_and_above": 100,
          "no_qualifications": 100,
          "other_qualifications": 100
        },
        "2021": {
          "apprenticeship": 4.3011,
          "level_1_qualifications": 5.7348,
          "level_2_qualifications": 14.3369,
          "level_3_qualifications": 20.6093,
          "level_4_qualifications_and_above": 29.9283,
          "no_qualifications": 23.4767,
          "other_qualifications": 1.6129
        }
      }
    },
    "car_or_van": {
      "perc": {
        "2011": {
          "five_or_more": 100,
          "four": 100,
          "none": 100,
          "one": 100,
          "three": 100,
          "two": 100
        },
        "2021": {
          "five_or_more": 0.7018,
          "four": 1.7544,
          "none": 7.3684,
          "one": 37.193,
          "three": 12.6316,
          "two": 40.3509
        }
      }
    },
    "mainlang": {
      "perc": {
        "2011": {
          "english": 100,
          "other_languages": 100
        },
        "2021": {
          "english": 99.7097,
          "other_languages": 0.2903
        }
      }
    },
    "age": {
      "perc": {
        "2011": {
          "a0to14": 100,
          "a15to39": 100,
          "a40to64": 100,
          "a65plus": 100
        },
        "2021": {
          "a0to14": 20.6416,
          "a15to39": 26.9177,
          "a40to64": 37.5174,
          "a65plus": 14.9233
        }
      }
    },
    "provision_care": {
      "perc": {
        "2011": {
          "a1to19_hours": 100,
          "a20to49_hours": 100,
          "a50plus_hours": 100,
          "no_care": 100
        },
        "2021": {
          "a1to19_hours": 7.2485,
          "a20to49_hours": 1.0355,
          "a50plus_hours": 3.9941,
          "no_care": 87.7219
        }
      }
    },
    "religion_or_religion_brought_up_in": {
      "perc": {
        "2011": {
          "catholic": 100,
          "none": 100,
          "other_religions": 100,
          "protestant_and_other_christian_including_christian_related": 100
        },
        "2021": {
          "catholic": 4.3236,
          "none": 9.484,
          "other_religions": 0.8368,
          "protestant_and_other_christian_including_christian_related": 85.3556
        }
      }
    },
    "renewable_energy": {
      "perc": {
        "2011": {
          "any_renewable": 100,
          "no_renewable": 100
        },
        "2021": {
          "any_renewable": 3.5211,
          "no_renewable": 96.4789
        }
      }
    },
    "sex": {
      "perc": {
        "2011": {
          "females": 100,
          "males": 100
        },
        "2021": {
          "females": 51.046,
          "males": 48.954
        }
      }
    },
    "BS": {
      "value": {
        "IS": 0,
        "JSA": 0,
        "RP": 100,
        "PC": 20,
        "AA": 20,
        "CA": 20,
        "DLA": 20,
        "ESA": 30,
        "UC": 60,
        "PIP": 60
      }
    },
    "MYETotal": {
      "value": 728
    }
  },
  "hectares": 784,
  "meta_data": {
    "MYETotal": [
      {
        "table_code": "MYE01T011",
        "dataset_url": "https://data.nisra.gov.uk/table/MYE01T011",
        "geog_level": "dz",
        "last_updated": "2024-07-30",
        "email": "census@nisra.gov.uk",
        "title": "Mid-year population estimates",
        "year": "2022"
      }
    ],
    "BS": [
      {
        "table_code": "BSDZ",
        "dataset_url": "https://data.nisra.gov.uk/table/BSDZ",
        "geog_level": "dz",
        "last_updated": "2023-07-06",
        "email": "psu@communities-ni.gov.uk",
        "title": "Benefit Statistics",
        "year": "2023"
      }
    ]
  }
}
