{
  "code": "N20000104",
  "name": "Ballyclare_C3",
  "comment": "This JSON includes data for the area explorer app.",
  "type": "dz",
  "count": 3780,
  "parents": [
    {
      "code": "N21000021",
      "name": "Ballyclare_C",
      "type": "sdz"
    },
    {
      "code": "N10000103",
      "name": "Ballyclare",
      "type": "dea"
    },
    {
      "code": "N09000001",
      "name": "Antrim and Newtownabbey",
      "type": "lgd"
    },
    {
      "code": "N92000002",
      "name": "Northern Ireland",
      "type": "ctry"
    }
  ],
  "children": [],
  "bounds": [
    [-6.0081, 54.7503],
    [-6.0168, 54.7554]
  ],
  "data": {
    "population": {
      "perc": {
        "2011": {
          "all": 100
        },
        "2021": {
          "all": 100
        }
      },
      "value": {
        "2011": {
          "all": 0
        },
        "change": {
          "all": "Inf"
        },
        "2021": {
          "all": 533
        }
      },
      "value_rank": {
        "2011": {
          "all": 0
        },
        "2021": {
          "all": 1467
        }
      }
    },
    "households": {
      "perc": {
        "2011": {
          "all_households": 100
        },
        "2021": {
          "all_households": 100
        }
      },
      "value": {
        "2011": {
          "all_households": 0
        },
        "change": {
          "all_households": "Inf"
        },
        "2021": {
          "all_households": 230
        }
      }
    },
    "cob": {
      "perc": {
        "2011": {
          "england": 100,
          "northern_ireland": 100,
          "other_cob": 100,
          "republic_of_ireland": 100,
          "scotland": 100,
          "wales": 100
        },
        "2021": {
          "england": 4.6904,
          "northern_ireland": 91.182,
          "other_cob": 2.2514,
          "republic_of_ireland": 0.3752,
          "scotland": 1.5009,
          "wales": 0
        }
      }
    },
    "general_health": {
      "perc": {
        "2011": {
          "bad": 100,
          "fair": 100,
          "good": 100,
          "very_bad": 100,
          "very_good": 100
        },
        "2021": {
          "bad": 8.2552,
          "fair": 15.197,
          "good": 27.955,
          "very_bad": 3.0019,
          "very_good": 45.591
        }
      }
    },
    "hh_size": {
      "perc": {
        "2011": {
          "five_people": 100,
          "four_people": 100,
          "one_person": 100,
          "three_people": 100,
          "two_people": 100
        },
        "2021": {
          "five_people": 7.8261,
          "four_people": 12.6087,
          "one_person": 36.087,
          "three_people": 12.1739,
          "two_people": 31.3043
        }
      }
    },
    "highest_level_of_qualifications": {
      "perc": {
        "2011": {
          "apprenticeship": 100,
          "level_1_qualifications": 100,
          "level_2_qualifications": 100,
          "level_3_qualifications": 100,
          "level_4_qualifications_and_above": 100,
          "no_qualifications": 100,
          "other_qualifications": 100
        },
        "2021": {
          "apprenticeship": 6.2016,
          "level_1_qualifications": 6.2016,
          "level_2_qualifications": 17.8295,
          "level_3_qualifications": 12.1447,
          "level_4_qualifications_and_above": 17.3127,
          "no_qualifications": 37.9845,
          "other_qualifications": 2.3256
        }
      }
    },
    "car_or_van": {
      "perc": {
        "2011": {
          "five_or_more": 100,
          "four": 100,
          "none": 100,
          "one": 100,
          "three": 100,
          "two": 100
        },
        "2021": {
          "five_or_more": 0,
          "four": 0,
          "none": 40,
          "one": 36.087,
          "three": 5.6522,
          "two": 18.2609
        }
      }
    },
    "mainlang": {
      "perc": {
        "2011": {
          "english": 100,
          "other_languages": 100
        },
        "2021": {
          "english": 99.4071,
          "other_languages": 0.5929
        }
      }
    },
    "age": {
      "perc": {
        "2011": {
          "a0to14": 100,
          "a15to39": 100,
          "a40to64": 100,
          "a65plus": 100
        },
        "2021": {
          "a0to14": 25.8427,
          "a15to39": 37.6404,
          "a40to64": 23.5955,
          "a65plus": 12.9213
        }
      }
    },
    "provision_care": {
      "perc": {
        "2011": {
          "a1to19_hours": 100,
          "a20to49_hours": 100,
          "a50plus_hours": 100,
          "no_care": 100
        },
        "2021": {
          "a1to19_hours": 3.4205,
          "a20to49_hours": 2.6157,
          "a50plus_hours": 6.0362,
          "no_care": 87.9276
        }
      }
    },
    "religion_or_religion_brought_up_in": {
      "perc": {
        "2011": {
          "catholic": 100,
          "none": 100,
          "other_religions": 100,
          "protestant_and_other_christian_including_christian_related": 100
        },
        "2021": {
          "catholic": 4.1276,
          "none": 20.6379,
          "other_religions": 0.9381,
          "protestant_and_other_christian_including_christian_related": 74.2964
        }
      }
    },
    "renewable_energy": {
      "perc": {
        "2011": {
          "any_renewable": 100,
          "no_renewable": 100
        },
        "2021": {
          "any_renewable": 0.8696,
          "no_renewable": 99.1304
        }
      }
    },
    "sex": {
      "perc": {
        "2011": {
          "females": 100,
          "males": 100
        },
        "2021": {
          "females": 53.6585,
          "males": 46.3415
        }
      }
    },
    "BS": {
      "value": {
        "IS": 10,
        "JSA": 0,
        "RP": 60,
        "PC": 20,
        "AA": 10,
        "CA": 30,
        "DLA": 30,
        "ESA": 50,
        "UC": 120,
        "PIP": 100
      }
    },
    "MYETotal": {
      "value": 547
    }
  },
  "hectares": 13,
  "meta_data": {
    "MYETotal": [
      {
        "table_code": "MYE01T011",
        "dataset_url": "https://data.nisra.gov.uk/table/MYE01T011",
        "geog_level": "dz",
        "last_updated": "2025-06-09",
        "email": "census@nisra.gov.uk",
        "title": "Mid-year population estimates",
        "year": "2023"
      }
    ],
    "BS": [
      {
        "table_code": "BSDZ",
        "dataset_url": "https://data.nisra.gov.uk/table/BSDZ",
        "geog_level": "dz",
        "last_updated": "2025-05-28",
        "email": "analyticsdivision@communities-ni.gov.uk",
        "title": "Benefit Statistics",
        "year": "2024"
      }
    ]
  }
}
