{
  "code": "N20002229",
  "name": "Mid_Tyrone_B5",
  "comment": "This JSON includes data for the area explorer app.",
  "type": "dz",
  "count": 3780,
  "parents": [
    {
      "code": "N21000505",
      "name": "Mid_Tyrone_B",
      "type": "sdz"
    },
    {
      "code": "N10000605",
      "name": "Mid Tyrone",
      "type": "dea"
    },
    {
      "code": "N09000006",
      "name": "Fermanagh and Omagh",
      "type": "lgd"
    },
    {
      "code": "N92000002",
      "name": "Northern Ireland",
      "type": "ctry"
    }
  ],
  "children": [],
  "bounds": [
    [-7.1618, 54.6354],
    [-7.2413, 54.6785]
  ],
  "data": {
    "population": {
      "perc": {
        "2011": {
          "all": 100
        },
        "2021": {
          "all": 100
        }
      },
      "value": {
        "2011": {
          "all": 0
        },
        "change": {
          "all": "Inf"
        },
        "2021": {
          "all": 433
        }
      },
      "value_rank": {
        "2011": {
          "all": 0
        },
        "2021": {
          "all": 2522
        }
      }
    },
    "households": {
      "perc": {
        "2011": {
          "all_households": 100
        },
        "2021": {
          "all_households": 100
        }
      },
      "value": {
        "2011": {
          "all_households": 0
        },
        "change": {
          "all_households": "Inf"
        },
        "2021": {
          "all_households": 150
        }
      }
    },
    "cob": {
      "perc": {
        "2011": {
          "england": 100,
          "northern_ireland": 100,
          "other_cob": 100,
          "republic_of_ireland": 100,
          "scotland": 100,
          "wales": 100
        },
        "2021": {
          "england": 3.2258,
          "northern_ireland": 89.1705,
          "other_cob": 4.6083,
          "republic_of_ireland": 2.5346,
          "scotland": 0.2304,
          "wales": 0.2304
        }
      }
    },
    "general_health": {
      "perc": {
        "2011": {
          "bad": 100,
          "fair": 100,
          "good": 100,
          "very_bad": 100,
          "very_good": 100
        },
        "2021": {
          "bad": 4.6189,
          "fair": 13.8568,
          "good": 23.0947,
          "very_bad": 0.9238,
          "very_good": 57.5058
        }
      }
    },
    "hh_size": {
      "perc": {
        "2011": {
          "five_people": 100,
          "four_people": 100,
          "one_person": 100,
          "three_people": 100,
          "two_people": 100
        },
        "2021": {
          "five_people": 14.6667,
          "four_people": 19.3333,
          "one_person": 22,
          "three_people": 22,
          "two_people": 22
        }
      }
    },
    "highest_level_of_qualifications": {
      "perc": {
        "2011": {
          "apprenticeship": 100,
          "level_1_qualifications": 100,
          "level_2_qualifications": 100,
          "level_3_qualifications": 100,
          "level_4_qualifications_and_above": 100,
          "no_qualifications": 100,
          "other_qualifications": 100
        },
        "2021": {
          "apprenticeship": 7.3394,
          "level_1_qualifications": 7.9511,
          "level_2_qualifications": 11.6208,
          "level_3_qualifications": 18.6544,
          "level_4_qualifications_and_above": 29.3578,
          "no_qualifications": 24.4648,
          "other_qualifications": 0.6116
        }
      }
    },
    "car_or_van": {
      "perc": {
        "2011": {
          "five_or_more": 100,
          "four": 100,
          "none": 100,
          "one": 100,
          "three": 100,
          "two": 100
        },
        "2021": {
          "five_or_more": 1.3333,
          "four": 2,
          "none": 6,
          "one": 34.6667,
          "three": 15.3333,
          "two": 40.6667
        }
      }
    },
    "mainlang": {
      "perc": {
        "2011": {
          "english": 100,
          "other_languages": 100
        },
        "2021": {
          "english": 97.561,
          "other_languages": 2.439
        }
      }
    },
    "age": {
      "perc": {
        "2011": {
          "a0to14": 100,
          "a15to39": 100,
          "a40to64": 100,
          "a65plus": 100
        },
        "2021": {
          "a0to14": 22.6328,
          "a15to39": 33.7182,
          "a40to64": 29.5612,
          "a65plus": 14.0878
        }
      }
    },
    "provision_care": {
      "perc": {
        "2011": {
          "a1to19_hours": 100,
          "a20to49_hours": 100,
          "a50plus_hours": 100,
          "no_care": 100
        },
        "2021": {
          "a1to19_hours": 3.2911,
          "a20to49_hours": 1.519,
          "a50plus_hours": 4.3038,
          "no_care": 90.8861
        }
      }
    },
    "religion_or_religion_brought_up_in": {
      "perc": {
        "2011": {
          "catholic": 100,
          "none": 100,
          "other_religions": 100,
          "protestant_and_other_christian_including_christian_related": 100
        },
        "2021": {
          "catholic": 91.4352,
          "none": 2.3148,
          "other_religions": 0.2315,
          "protestant_and_other_christian_including_christian_related": 6.0185
        }
      }
    },
    "renewable_energy": {
      "perc": {
        "2011": {
          "any_renewable": 100,
          "no_renewable": 100
        },
        "2021": {
          "any_renewable": 8,
          "no_renewable": 92
        }
      }
    },
    "sex": {
      "perc": {
        "2011": {
          "females": 100,
          "males": 100
        },
        "2021": {
          "females": 51.7321,
          "males": 48.2679
        }
      }
    },
    "BS": {
      "value": {
        "IS": 10,
        "JSA": 0,
        "RP": 50,
        "PC": 10,
        "AA": 10,
        "CA": 30,
        "DLA": 20,
        "ESA": 20,
        "UC": 30,
        "PIP": 50
      }
    },
    "MYETotal": {
      "value": 433
    }
  },
  "hectares": 1428,
  "meta_data": {
    "MYETotal": [
      {
        "table_code": "MYE01T011",
        "dataset_url": "https://data.nisra.gov.uk/table/MYE01T011",
        "geog_level": "dz",
        "last_updated": "2025-06-09",
        "email": "census@nisra.gov.uk",
        "title": "Mid-year population estimates",
        "year": "2023"
      }
    ],
    "BS": [
      {
        "table_code": "BSDZ",
        "dataset_url": "https://data.nisra.gov.uk/table/BSDZ",
        "geog_level": "dz",
        "last_updated": "2025-05-28",
        "email": "analyticsdivision@communities-ni.gov.uk",
        "title": "Benefit Statistics",
        "year": "2024"
      }
    ]
  }
}
