{
  "code": "N20002044",
  "name": "Erne_East_E1",
  "comment": "This JSON includes data for the area explorer app.",
  "type": "dz",
  "count": 3780,
  "parents": [
    {
      "code": "N21000466",
      "name": "Erne_East_E",
      "type": "sdz"
    },
    {
      "code": "N10000602",
      "name": "Erne East",
      "type": "dea"
    },
    {
      "code": "N09000006",
      "name": "Fermanagh and Omagh",
      "type": "lgd"
    },
    {
      "code": "N92000002",
      "name": "Northern Ireland",
      "type": "ctry"
    }
  ],
  "children": [],
  "bounds": [
    [-7.3787, 54.2144],
    [-7.4379, 54.2843]
  ],
  "data": {
    "population": {
      "perc": {
        "2011": {
          "all": 100
        },
        "2021": {
          "all": 100
        }
      },
      "value": {
        "2011": {
          "all": 0
        },
        "change": {
          "all": "Inf"
        },
        "2021": {
          "all": 524
        }
      },
      "value_rank": {
        "2011": {
          "all": 0
        },
        "2021": {
          "all": 1556
        }
      }
    },
    "households": {
      "perc": {
        "2011": {
          "all_households": 100
        },
        "2021": {
          "all_households": 100
        }
      },
      "value": {
        "2011": {
          "all_households": 0
        },
        "change": {
          "all_households": "Inf"
        },
        "2021": {
          "all_households": 192
        }
      }
    },
    "cob": {
      "perc": {
        "2011": {
          "england": 100,
          "northern_ireland": 100,
          "other_cob": 100,
          "republic_of_ireland": 100,
          "scotland": 100,
          "wales": 100
        },
        "2021": {
          "england": 2.8626,
          "northern_ireland": 89.1221,
          "other_cob": 1.145,
          "republic_of_ireland": 6.4885,
          "scotland": 0.1908,
          "wales": 0.1908
        }
      }
    },
    "general_health": {
      "perc": {
        "2011": {
          "bad": 100,
          "fair": 100,
          "good": 100,
          "very_bad": 100,
          "very_good": 100
        },
        "2021": {
          "bad": 5.3435,
          "fair": 11.4504,
          "good": 23.855,
          "very_bad": 2.0992,
          "very_good": 57.2519
        }
      }
    },
    "hh_size": {
      "perc": {
        "2011": {
          "five_people": 100,
          "four_people": 100,
          "one_person": 100,
          "three_people": 100,
          "two_people": 100
        },
        "2021": {
          "five_people": 16.7539,
          "four_people": 14.6597,
          "one_person": 28.7958,
          "three_people": 12.0419,
          "two_people": 27.7487
        }
      }
    },
    "highest_level_of_qualifications": {
      "perc": {
        "2011": {
          "apprenticeship": 100,
          "level_1_qualifications": 100,
          "level_2_qualifications": 100,
          "level_3_qualifications": 100,
          "level_4_qualifications_and_above": 100,
          "no_qualifications": 100,
          "other_qualifications": 100
        },
        "2021": {
          "apprenticeship": 4.7382,
          "level_1_qualifications": 4.9875,
          "level_2_qualifications": 13.217,
          "level_3_qualifications": 13.217,
          "level_4_qualifications_and_above": 34.1646,
          "no_qualifications": 28.1796,
          "other_qualifications": 1.4963
        }
      }
    },
    "car_or_van": {
      "perc": {
        "2011": {
          "five_or_more": 100,
          "four": 100,
          "none": 100,
          "one": 100,
          "three": 100,
          "two": 100
        },
        "2021": {
          "five_or_more": 4.6875,
          "four": 3.6458,
          "none": 8.8542,
          "one": 34.8958,
          "three": 10.9375,
          "two": 36.9792
        }
      }
    },
    "mainlang": {
      "perc": {
        "2011": {
          "english": 100,
          "other_languages": 100
        },
        "2021": {
          "english": 99.0119,
          "other_languages": 0.9881
        }
      }
    },
    "age": {
      "perc": {
        "2011": {
          "a0to14": 100,
          "a15to39": 100,
          "a40to64": 100,
          "a65plus": 100
        },
        "2021": {
          "a0to14": 22.5191,
          "a15to39": 25.7634,
          "a40to64": 32.8244,
          "a65plus": 18.8931
        }
      }
    },
    "provision_care": {
      "perc": {
        "2011": {
          "a1to19_hours": 100,
          "a20to49_hours": 100,
          "a50plus_hours": 100,
          "no_care": 100
        },
        "2021": {
          "a1to19_hours": 5.102,
          "a20to49_hours": 1.4286,
          "a50plus_hours": 4.6939,
          "no_care": 88.7755
        }
      }
    },
    "religion_or_religion_brought_up_in": {
      "perc": {
        "2011": {
          "catholic": 100,
          "none": 100,
          "other_religions": 100,
          "protestant_and_other_christian_including_christian_related": 100
        },
        "2021": {
          "catholic": 72.3282,
          "none": 0,
          "other_religions": 0,
          "protestant_and_other_christian_including_christian_related": 27.6718
        }
      }
    },
    "renewable_energy": {
      "perc": {
        "2011": {
          "any_renewable": 100,
          "no_renewable": 100
        },
        "2021": {
          "any_renewable": 13.0208,
          "no_renewable": 86.9792
        }
      }
    },
    "sex": {
      "perc": {
        "2011": {
          "females": 100,
          "males": 100
        },
        "2021": {
          "females": 51.7176,
          "males": 48.2824
        }
      }
    },
    "BS": {
      "value": {
        "IS": 0,
        "JSA": 0,
        "RP": 90,
        "PC": 30,
        "AA": 20,
        "CA": 30,
        "DLA": 40,
        "ESA": 20,
        "UC": 30,
        "PIP": 50
      }
    },
    "MYETotal": {
      "value": 525
    }
  },
  "hectares": 1559,
  "meta_data": {
    "MYETotal": [
      {
        "table_code": "MYE01T011",
        "dataset_url": "https://data.nisra.gov.uk/table/MYE01T011",
        "geog_level": "dz",
        "last_updated": "2025-06-09",
        "email": "census@nisra.gov.uk",
        "title": "Mid-year population estimates",
        "year": "2023"
      }
    ],
    "BS": [
      {
        "table_code": "BSDZ",
        "dataset_url": "https://data.nisra.gov.uk/table/BSDZ",
        "geog_level": "dz",
        "last_updated": "2025-05-28",
        "email": "analyticsdivision@communities-ni.gov.uk",
        "title": "Benefit Statistics",
        "year": "2024"
      }
    ]
  }
}
