{
  "code": "N20002207",
  "name": "Omagh_E5",
  "comment": "This JSON includes data for the area explorer app.",
  "type": "dz",
  "count": 3780,
  "parents": [
    {
      "code": "N21000500",
      "name": "Omagh_E",
      "type": "sdz"
    },
    {
      "code": "N10000606",
      "name": "Omagh",
      "type": "dea"
    },
    {
      "code": "N09000006",
      "name": "Fermanagh and Omagh",
      "type": "lgd"
    },
    {
      "code": "N92000002",
      "name": "Northern Ireland",
      "type": "ctry"
    }
  ],
  "children": [],
  "bounds": [
    [-7.2533, 54.5886],
    [-7.2712, 54.6022]
  ],
  "data": {
    "population": {
      "perc": {
        "2011": {
          "all": 100
        },
        "2021": {
          "all": 100
        }
      },
      "value": {
        "2011": {
          "all": 0
        },
        "change": {
          "all": "Inf"
        },
        "2021": {
          "all": 451
        }
      },
      "value_rank": {
        "2011": {
          "all": 0
        },
        "2021": {
          "all": 2328
        }
      }
    },
    "households": {
      "perc": {
        "2011": {
          "all_households": 100
        },
        "2021": {
          "all_households": 100
        }
      },
      "value": {
        "2011": {
          "all_households": 0
        },
        "change": {
          "all_households": "Inf"
        },
        "2021": {
          "all_households": 187
        }
      }
    },
    "cob": {
      "perc": {
        "2011": {
          "england": 100,
          "northern_ireland": 100,
          "other_cob": 100,
          "republic_of_ireland": 100,
          "scotland": 100,
          "wales": 100
        },
        "2021": {
          "england": 6.264,
          "northern_ireland": 85.6823,
          "other_cob": 6.264,
          "republic_of_ireland": 0.8949,
          "scotland": 0.8949,
          "wales": 0
        }
      }
    },
    "general_health": {
      "perc": {
        "2011": {
          "bad": 100,
          "fair": 100,
          "good": 100,
          "very_bad": 100,
          "very_good": 100
        },
        "2021": {
          "bad": 6.2084,
          "fair": 14.6341,
          "good": 32.1508,
          "very_bad": 1.5521,
          "very_good": 45.4545
        }
      }
    },
    "hh_size": {
      "perc": {
        "2011": {
          "five_people": 100,
          "four_people": 100,
          "one_person": 100,
          "three_people": 100,
          "two_people": 100
        },
        "2021": {
          "five_people": 5.8824,
          "four_people": 11.2299,
          "one_person": 34.2246,
          "three_people": 16.0428,
          "two_people": 32.6203
        }
      }
    },
    "highest_level_of_qualifications": {
      "perc": {
        "2011": {
          "apprenticeship": 100,
          "level_1_qualifications": 100,
          "level_2_qualifications": 100,
          "level_3_qualifications": 100,
          "level_4_qualifications_and_above": 100,
          "no_qualifications": 100,
          "other_qualifications": 100
        },
        "2021": {
          "apprenticeship": 7.6923,
          "level_1_qualifications": 4.5093,
          "level_2_qualifications": 10.8753,
          "level_3_qualifications": 14.3236,
          "level_4_qualifications_and_above": 31.8302,
          "no_qualifications": 28.9125,
          "other_qualifications": 1.8568
        }
      }
    },
    "car_or_van": {
      "perc": {
        "2011": {
          "five_or_more": 100,
          "four": 100,
          "none": 100,
          "one": 100,
          "three": 100,
          "two": 100
        },
        "2021": {
          "five_or_more": 0,
          "four": 1.0753,
          "none": 24.7312,
          "one": 34.9462,
          "three": 5.3763,
          "two": 33.871
        }
      }
    },
    "mainlang": {
      "perc": {
        "2011": {
          "english": 100,
          "other_languages": 100
        },
        "2021": {
          "english": 96.9626,
          "other_languages": 3.0374
        }
      }
    },
    "age": {
      "perc": {
        "2011": {
          "a0to14": 100,
          "a15to39": 100,
          "a40to64": 100,
          "a65plus": 100
        },
        "2021": {
          "a0to14": 15.5211,
          "a15to39": 37.694,
          "a40to64": 30.3769,
          "a65plus": 16.408
        }
      }
    },
    "provision_care": {
      "perc": {
        "2011": {
          "a1to19_hours": 100,
          "a20to49_hours": 100,
          "a50plus_hours": 100,
          "no_care": 100
        },
        "2021": {
          "a1to19_hours": 3.0733,
          "a20to49_hours": 4.0189,
          "a50plus_hours": 5.6738,
          "no_care": 87.234
        }
      }
    },
    "religion_or_religion_brought_up_in": {
      "perc": {
        "2011": {
          "catholic": 100,
          "none": 100,
          "other_religions": 100,
          "protestant_and_other_christian_including_christian_related": 100
        },
        "2021": {
          "catholic": 51.5487,
          "none": 6.4159,
          "other_religions": 0,
          "protestant_and_other_christian_including_christian_related": 42.0354
        }
      }
    },
    "renewable_energy": {
      "perc": {
        "2011": {
          "any_renewable": 100,
          "no_renewable": 100
        },
        "2021": {
          "any_renewable": 1.0753,
          "no_renewable": 98.9247
        }
      }
    },
    "sex": {
      "perc": {
        "2011": {
          "females": 100,
          "males": 100
        },
        "2021": {
          "females": 49.4457,
          "males": 50.5543
        }
      }
    },
    "BS": {
      "value": {
        "IS": 0,
        "JSA": 0,
        "RP": 40,
        "PC": 10,
        "AA": 0,
        "CA": 20,
        "DLA": 20,
        "ESA": 60,
        "UC": 60,
        "PIP": 100
      }
    },
    "MYETotal": {
      "value": 478
    }
  },
  "hectares": 100,
  "meta_data": {
    "MYETotal": [
      {
        "table_code": "MYE01T011",
        "dataset_url": "https://data.nisra.gov.uk/table/MYE01T011",
        "geog_level": "dz",
        "last_updated": "2024-07-30",
        "email": "census@nisra.gov.uk",
        "title": "Mid-year population estimates",
        "year": "2022"
      }
    ],
    "BS": [
      {
        "table_code": "BSDZ",
        "dataset_url": "https://data.nisra.gov.uk/table/BSDZ",
        "geog_level": "dz",
        "last_updated": "2024-09-24",
        "email": "analyticsdivision@communities-ni.gov.uk",
        "title": "Benefit Statistics",
        "year": "2024"
      }
    ]
  }
}
