{
  "code": "N20000670",
  "name": "Cusher_A2",
  "comment": "This JSON includes data for the area explorer app.",
  "type": "dz",
  "count": 3780,
  "parents": [
    {
      "code": "N21000150",
      "name": "Cusher_A",
      "type": "sdz"
    },
    {
      "code": "N10000204",
      "name": "Cusher",
      "type": "dea"
    },
    {
      "code": "N09000002",
      "name": "Armagh City, Banbridge and Craigavon",
      "type": "lgd"
    },
    {
      "code": "N92000002",
      "name": "Northern Ireland",
      "type": "ctry"
    }
  ],
  "children": [],
  "bounds": [
    [-6.4459, 54.3682],
    [-6.4566, 54.3737]
  ],
  "data": {
    "population": {
      "perc": {
        "2011": {
          "all": 100
        },
        "2021": {
          "all": 100
        }
      },
      "value": {
        "2011": {
          "all": 0
        },
        "change": {
          "all": "Inf"
        },
        "2021": {
          "all": 484
        }
      },
      "value_rank": {
        "2011": {
          "all": 0
        },
        "2021": {
          "all": 1959
        }
      }
    },
    "households": {
      "perc": {
        "2011": {
          "all_households": 100
        },
        "2021": {
          "all_households": 100
        }
      },
      "value": {
        "2011": {
          "all_households": 0
        },
        "change": {
          "all_households": "Inf"
        },
        "2021": {
          "all_households": 175
        }
      }
    },
    "cob": {
      "perc": {
        "2011": {
          "england": 100,
          "northern_ireland": 100,
          "other_cob": 100,
          "republic_of_ireland": 100,
          "scotland": 100,
          "wales": 100
        },
        "2021": {
          "england": 2.8926,
          "northern_ireland": 91.5289,
          "other_cob": 4.3388,
          "republic_of_ireland": 0.6198,
          "scotland": 0.6198,
          "wales": 0
        }
      }
    },
    "general_health": {
      "perc": {
        "2011": {
          "bad": 100,
          "fair": 100,
          "good": 100,
          "very_bad": 100,
          "very_good": 100
        },
        "2021": {
          "bad": 4.3388,
          "fair": 8.2645,
          "good": 29.5455,
          "very_bad": 0.4132,
          "very_good": 57.438
        }
      }
    },
    "hh_size": {
      "perc": {
        "2011": {
          "five_people": 100,
          "four_people": 100,
          "one_person": 100,
          "three_people": 100,
          "two_people": 100
        },
        "2021": {
          "five_people": 9.7143,
          "four_people": 22.8571,
          "one_person": 17.7143,
          "three_people": 18.8571,
          "two_people": 30.8571
        }
      }
    },
    "highest_level_of_qualifications": {
      "perc": {
        "2011": {
          "apprenticeship": 100,
          "level_1_qualifications": 100,
          "level_2_qualifications": 100,
          "level_3_qualifications": 100,
          "level_4_qualifications_and_above": 100,
          "no_qualifications": 100,
          "other_qualifications": 100
        },
        "2021": {
          "apprenticeship": 3.6313,
          "level_1_qualifications": 4.7486,
          "level_2_qualifications": 18.1564,
          "level_3_qualifications": 20.9497,
          "level_4_qualifications_and_above": 29.8883,
          "no_qualifications": 20.3911,
          "other_qualifications": 2.2346
        }
      }
    },
    "car_or_van": {
      "perc": {
        "2011": {
          "five_or_more": 100,
          "four": 100,
          "none": 100,
          "one": 100,
          "three": 100,
          "two": 100
        },
        "2021": {
          "five_or_more": 0.5714,
          "four": 4.5714,
          "none": 5.1429,
          "one": 33.1429,
          "three": 16.5714,
          "two": 40
        }
      }
    },
    "mainlang": {
      "perc": {
        "2011": {
          "english": 100,
          "other_languages": 100
        },
        "2021": {
          "english": 96.5591,
          "other_languages": 3.4409
        }
      }
    },
    "age": {
      "perc": {
        "2011": {
          "a0to14": 100,
          "a15to39": 100,
          "a40to64": 100,
          "a65plus": 100
        },
        "2021": {
          "a0to14": 24.2236,
          "a15to39": 32.0911,
          "a40to64": 34.7826,
          "a65plus": 8.9027
        }
      }
    },
    "provision_care": {
      "perc": {
        "2011": {
          "a1to19_hours": 100,
          "a20to49_hours": 100,
          "a50plus_hours": 100,
          "no_care": 100
        },
        "2021": {
          "a1to19_hours": 6.5315,
          "a20to49_hours": 2.027,
          "a50plus_hours": 3.1532,
          "no_care": 88.2883
        }
      }
    },
    "religion_or_religion_brought_up_in": {
      "perc": {
        "2011": {
          "catholic": 100,
          "none": 100,
          "other_religions": 100,
          "protestant_and_other_christian_including_christian_related": 100
        },
        "2021": {
          "catholic": 8.4711,
          "none": 9.2975,
          "other_religions": 0,
          "protestant_and_other_christian_including_christian_related": 82.2314
        }
      }
    },
    "renewable_energy": {
      "perc": {
        "2011": {
          "any_renewable": 100,
          "no_renewable": 100
        },
        "2021": {
          "any_renewable": 0.5714,
          "no_renewable": 99.4286
        }
      }
    },
    "sex": {
      "perc": {
        "2011": {
          "females": 100,
          "males": 100
        },
        "2021": {
          "females": 50.4132,
          "males": 49.5868
        }
      }
    },
    "BS": {
      "value": {
        "IS": 0,
        "JSA": 0,
        "RP": 40,
        "PC": 10,
        "AA": 10,
        "CA": 10,
        "DLA": 10,
        "ESA": 20,
        "UC": 30,
        "PIP": 30
      }
    },
    "MYETotal": {
      "value": 553
    }
  },
  "hectares": 23,
  "meta_data": {
    "MYETotal": [
      {
        "table_code": "MYE01T011",
        "dataset_url": "https://data.nisra.gov.uk/table/MYE01T011",
        "geog_level": "dz",
        "last_updated": "2025-06-09",
        "email": "census@nisra.gov.uk",
        "title": "Mid-year population estimates",
        "year": "2023"
      }
    ],
    "BS": [
      {
        "table_code": "BSDZ",
        "dataset_url": "https://data.nisra.gov.uk/table/BSDZ",
        "geog_level": "dz",
        "last_updated": "2025-05-28",
        "email": "analyticsdivision@communities-ni.gov.uk",
        "title": "Benefit Statistics",
        "year": "2024"
      }
    ]
  }
}
