{
  "code": "N20000064",
  "name": "Antrim_J2",
  "comment": "This JSON includes data for the area explorer app.",
  "type": "dz",
  "count": 3780,
  "parents": [
    {
      "code": "N21000015",
      "name": "Antrim_J",
      "type": "sdz"
    },
    {
      "code": "N10000102",
      "name": "Antrim",
      "type": "dea"
    },
    {
      "code": "N09000001",
      "name": "Antrim and Newtownabbey",
      "type": "lgd"
    },
    {
      "code": "N92000002",
      "name": "Northern Ireland",
      "type": "ctry"
    }
  ],
  "children": [],
  "bounds": [
    [-6.1895, 54.711],
    [-6.1941, 54.7156]
  ],
  "data": {
    "population": {
      "perc": {
        "2011": {
          "all": 100
        },
        "2021": {
          "all": 100
        }
      },
      "value": {
        "2011": {
          "all": 0
        },
        "change": {
          "all": "Inf"
        },
        "2021": {
          "all": 391
        }
      },
      "value_rank": {
        "2011": {
          "all": 0
        },
        "2021": {
          "all": 2922
        }
      }
    },
    "households": {
      "perc": {
        "2011": {
          "all_households": 100
        },
        "2021": {
          "all_households": 100
        }
      },
      "value": {
        "2011": {
          "all_households": 0
        },
        "change": {
          "all_households": "Inf"
        },
        "2021": {
          "all_households": 173
        }
      }
    },
    "cob": {
      "perc": {
        "2011": {
          "england": 100,
          "northern_ireland": 100,
          "other_cob": 100,
          "republic_of_ireland": 100,
          "scotland": 100,
          "wales": 100
        },
        "2021": {
          "england": 6.9231,
          "northern_ireland": 83.3333,
          "other_cob": 8.2051,
          "republic_of_ireland": 0.5128,
          "scotland": 1.0256,
          "wales": 0
        }
      }
    },
    "general_health": {
      "perc": {
        "2011": {
          "bad": 100,
          "fair": 100,
          "good": 100,
          "very_bad": 100,
          "very_good": 100
        },
        "2021": {
          "bad": 7.1429,
          "fair": 17.602,
          "good": 35.4592,
          "very_bad": 1.7857,
          "very_good": 38.0102
        }
      }
    },
    "hh_size": {
      "perc": {
        "2011": {
          "five_people": 100,
          "four_people": 100,
          "one_person": 100,
          "three_people": 100,
          "two_people": 100
        },
        "2021": {
          "five_people": 5.1724,
          "four_people": 9.1954,
          "one_person": 25.2874,
          "three_people": 17.8161,
          "two_people": 42.5287
        }
      }
    },
    "highest_level_of_qualifications": {
      "perc": {
        "2011": {
          "apprenticeship": 100,
          "level_1_qualifications": 100,
          "level_2_qualifications": 100,
          "level_3_qualifications": 100,
          "level_4_qualifications_and_above": 100,
          "no_qualifications": 100,
          "other_qualifications": 100
        },
        "2021": {
          "apprenticeship": 8.547,
          "level_1_qualifications": 5.1282,
          "level_2_qualifications": 13.1054,
          "level_3_qualifications": 14.8148,
          "level_4_qualifications_and_above": 30.4843,
          "no_qualifications": 25.3561,
          "other_qualifications": 2.5641
        }
      }
    },
    "car_or_van": {
      "perc": {
        "2011": {
          "five_or_more": 100,
          "four": 100,
          "none": 100,
          "one": 100,
          "three": 100,
          "two": 100
        },
        "2021": {
          "five_or_more": 0.578,
          "four": 2.3121,
          "none": 9.8266,
          "one": 49.1329,
          "three": 7.5145,
          "two": 30.6358
        }
      }
    },
    "mainlang": {
      "perc": {
        "2011": {
          "english": 100,
          "other_languages": 100
        },
        "2021": {
          "english": 94.5312,
          "other_languages": 5.4688
        }
      }
    },
    "age": {
      "perc": {
        "2011": {
          "a0to14": 100,
          "a15to39": 100,
          "a40to64": 100,
          "a65plus": 100
        },
        "2021": {
          "a0to14": 9.6939,
          "a15to39": 25.7653,
          "a40to64": 32.398,
          "a65plus": 32.1429
        }
      }
    },
    "provision_care": {
      "perc": {
        "2011": {
          "a1to19_hours": 100,
          "a20to49_hours": 100,
          "a50plus_hours": 100,
          "no_care": 100
        },
        "2021": {
          "a1to19_hours": 4.7368,
          "a20to49_hours": 4.7368,
          "a50plus_hours": 3.9474,
          "no_care": 86.5789
        }
      }
    },
    "religion_or_religion_brought_up_in": {
      "perc": {
        "2011": {
          "catholic": 100,
          "none": 100,
          "other_religions": 100,
          "protestant_and_other_christian_including_christian_related": 100
        },
        "2021": {
          "catholic": 33.6735,
          "none": 13.0102,
          "other_religions": 1.5306,
          "protestant_and_other_christian_including_christian_related": 51.7857
        }
      }
    },
    "renewable_energy": {
      "perc": {
        "2011": {
          "any_renewable": 100,
          "no_renewable": 100
        },
        "2021": {
          "any_renewable": 2.8736,
          "no_renewable": 97.1264
        }
      }
    },
    "sex": {
      "perc": {
        "2011": {
          "females": 100,
          "males": 100
        },
        "2021": {
          "females": 49.8721,
          "males": 50.1279
        }
      }
    },
    "BS": {
      "value": {
        "IS": 0,
        "JSA": 0,
        "RP": 100,
        "PC": 10,
        "AA": 20,
        "CA": 20,
        "DLA": 10,
        "ESA": 20,
        "UC": 10,
        "PIP": 40
      }
    },
    "MYETotal": {
      "value": 386
    }
  },
  "hectares": 9,
  "meta_data": {
    "MYETotal": [
      {
        "table_code": "MYE01T011",
        "dataset_url": "https://data.nisra.gov.uk/table/MYE01T011",
        "geog_level": "dz",
        "last_updated": "2024-07-30",
        "email": "census@nisra.gov.uk",
        "title": "Mid-year population estimates",
        "year": "2022"
      }
    ],
    "BS": [
      {
        "table_code": "BSDZ",
        "dataset_url": "https://data.nisra.gov.uk/table/BSDZ",
        "geog_level": "dz",
        "last_updated": "2023-07-06",
        "email": "psu@communities-ni.gov.uk",
        "title": "Benefit Statistics",
        "year": "2023"
      }
    ]
  }
}
