{
  "code": "N20000582",
  "name": "Lagan_River_K2",
  "comment": "This JSON includes data for the area explorer app.",
  "type": "dz",
  "count": 3780,
  "parents": [
    {
      "code": "N21000133",
      "name": "Lagan_River_K",
      "type": "sdz"
    },
    {
      "code": "N10000205",
      "name": "Lagan River",
      "type": "dea"
    },
    {
      "code": "N09000002",
      "name": "Armagh City, Banbridge and Craigavon",
      "type": "lgd"
    },
    {
      "code": "N92000002",
      "name": "Northern Ireland",
      "type": "ctry"
    }
  ],
  "children": [],
  "bounds": [
    [-6.0539, 54.3741],
    [-6.1262, 54.4122]
  ],
  "data": {
    "population": {
      "perc": {
        "2011": {
          "all": 100
        },
        "2021": {
          "all": 100
        }
      },
      "value": {
        "2011": {
          "all": 0
        },
        "change": {
          "all": "Inf"
        },
        "2021": {
          "all": 650
        }
      },
      "value_rank": {
        "2011": {
          "all": 0
        },
        "2021": {
          "all": 588
        }
      }
    },
    "households": {
      "perc": {
        "2011": {
          "all_households": 100
        },
        "2021": {
          "all_households": 100
        }
      },
      "value": {
        "2011": {
          "all_households": 0
        },
        "change": {
          "all_households": "Inf"
        },
        "2021": {
          "all_households": 218
        }
      }
    },
    "cob": {
      "perc": {
        "2011": {
          "england": 100,
          "northern_ireland": 100,
          "other_cob": 100,
          "republic_of_ireland": 100,
          "scotland": 100,
          "wales": 100
        },
        "2021": {
          "england": 2.4691,
          "northern_ireland": 94.7531,
          "other_cob": 1.8519,
          "republic_of_ireland": 0.6173,
          "scotland": 0.1543,
          "wales": 0.1543
        }
      }
    },
    "general_health": {
      "perc": {
        "2011": {
          "bad": 100,
          "fair": 100,
          "good": 100,
          "very_bad": 100,
          "very_good": 100
        },
        "2021": {
          "bad": 3.2308,
          "fair": 11.2308,
          "good": 27.2308,
          "very_bad": 0.7692,
          "very_good": 57.5385
        }
      }
    },
    "hh_size": {
      "perc": {
        "2011": {
          "five_people": 100,
          "four_people": 100,
          "one_person": 100,
          "three_people": 100,
          "two_people": 100
        },
        "2021": {
          "five_people": 16.055,
          "four_people": 20.1835,
          "one_person": 14.6789,
          "three_people": 16.5138,
          "two_people": 32.5688
        }
      }
    },
    "highest_level_of_qualifications": {
      "perc": {
        "2011": {
          "apprenticeship": 100,
          "level_1_qualifications": 100,
          "level_2_qualifications": 100,
          "level_3_qualifications": 100,
          "level_4_qualifications_and_above": 100,
          "no_qualifications": 100,
          "other_qualifications": 100
        },
        "2021": {
          "apprenticeship": 7.014,
          "level_1_qualifications": 6.8136,
          "level_2_qualifications": 12.2244,
          "level_3_qualifications": 17.8357,
          "level_4_qualifications_and_above": 38.8778,
          "no_qualifications": 16.0321,
          "other_qualifications": 1.2024
        }
      }
    },
    "car_or_van": {
      "perc": {
        "2011": {
          "five_or_more": 100,
          "four": 100,
          "none": 100,
          "one": 100,
          "three": 100,
          "two": 100
        },
        "2021": {
          "five_or_more": 3.2558,
          "four": 6.9767,
          "none": 1.8605,
          "one": 20.4651,
          "three": 20,
          "two": 47.4419
        }
      }
    },
    "mainlang": {
      "perc": {
        "2011": {
          "english": 100,
          "other_languages": 100
        },
        "2021": {
          "english": 99.685,
          "other_languages": 0.315
        }
      }
    },
    "age": {
      "perc": {
        "2011": {
          "a0to14": 100,
          "a15to39": 100,
          "a40to64": 100,
          "a65plus": 100
        },
        "2021": {
          "a0to14": 22,
          "a15to39": 25.5385,
          "a40to64": 36.7692,
          "a65plus": 15.6923
        }
      }
    },
    "provision_care": {
      "perc": {
        "2011": {
          "a1to19_hours": 100,
          "a20to49_hours": 100,
          "a50plus_hours": 100,
          "no_care": 100
        },
        "2021": {
          "a1to19_hours": 8.8853,
          "a20to49_hours": 3.0695,
          "a50plus_hours": 3.231,
          "no_care": 84.8142
        }
      }
    },
    "religion_or_religion_brought_up_in": {
      "perc": {
        "2011": {
          "catholic": 100,
          "none": 100,
          "other_religions": 100,
          "protestant_and_other_christian_including_christian_related": 100
        },
        "2021": {
          "catholic": 13.6923,
          "none": 8.4615,
          "other_religions": 1.0769,
          "protestant_and_other_christian_including_christian_related": 76.7692
        }
      }
    },
    "renewable_energy": {
      "perc": {
        "2011": {
          "any_renewable": 100,
          "no_renewable": 100
        },
        "2021": {
          "any_renewable": 15.1376,
          "no_renewable": 84.8624
        }
      }
    },
    "sex": {
      "perc": {
        "2011": {
          "females": 100,
          "males": 100
        },
        "2021": {
          "females": 50.1538,
          "males": 49.8462
        }
      }
    },
    "BS": {
      "value": {
        "IS": 0,
        "JSA": 0,
        "RP": 100,
        "PC": 10,
        "AA": 20,
        "CA": 20,
        "DLA": 10,
        "ESA": 20,
        "UC": 20,
        "PIP": 50
      }
    },
    "MYETotal": {
      "value": 640
    }
  },
  "hectares": 1077,
  "meta_data": {
    "MYETotal": [
      {
        "table_code": "MYE01T011",
        "dataset_url": "https://data.nisra.gov.uk/table/MYE01T011",
        "geog_level": "dz",
        "last_updated": "2025-06-09",
        "email": "census@nisra.gov.uk",
        "title": "Mid-year population estimates",
        "year": "2023"
      }
    ],
    "BS": [
      {
        "table_code": "BSDZ",
        "dataset_url": "https://data.nisra.gov.uk/table/BSDZ",
        "geog_level": "dz",
        "last_updated": "2025-05-28",
        "email": "analyticsdivision@communities-ni.gov.uk",
        "title": "Benefit Statistics",
        "year": "2024"
      }
    ]
  }
}
