{
  "code": "N20000041",
  "name": "Antrim_C1",
  "comment": "This JSON includes data for the area explorer app.",
  "type": "dz",
  "count": 3780,
  "parents": [
    {
      "code": "N21000009",
      "name": "Antrim_C",
      "type": "sdz"
    },
    {
      "code": "N10000102",
      "name": "Antrim",
      "type": "dea"
    },
    {
      "code": "N09000001",
      "name": "Antrim and Newtownabbey",
      "type": "lgd"
    },
    {
      "code": "N92000002",
      "name": "Northern Ireland",
      "type": "ctry"
    }
  ],
  "children": [],
  "bounds": [
    [-6.214, 54.7262],
    [-6.2387, 54.7357]
  ],
  "data": {
    "population": {
      "perc": {
        "2011": {
          "all": 100
        },
        "2021": {
          "all": 100
        }
      },
      "value": {
        "2011": {
          "all": 0
        },
        "change": {
          "all": "Inf"
        },
        "2021": {
          "all": 931
        }
      },
      "value_rank": {
        "2011": {
          "all": 0
        },
        "2021": {
          "all": 22
        }
      }
    },
    "households": {
      "perc": {
        "2011": {
          "all_households": 100
        },
        "2021": {
          "all_households": 100
        }
      },
      "value": {
        "2011": {
          "all_households": 0
        },
        "change": {
          "all_households": "Inf"
        },
        "2021": {
          "all_households": 333
        }
      }
    },
    "cob": {
      "perc": {
        "2011": {
          "england": 100,
          "northern_ireland": 100,
          "other_cob": 100,
          "republic_of_ireland": 100,
          "scotland": 100,
          "wales": 100
        },
        "2021": {
          "england": 5.2632,
          "northern_ireland": 80.666,
          "other_cob": 11.8153,
          "republic_of_ireland": 0.8593,
          "scotland": 1.0741,
          "wales": 0.3222
        }
      }
    },
    "general_health": {
      "perc": {
        "2011": {
          "bad": 100,
          "fair": 100,
          "good": 100,
          "very_bad": 100,
          "very_good": 100
        },
        "2021": {
          "bad": 3.8668,
          "fair": 10.956,
          "good": 29.8604,
          "very_bad": 1.2889,
          "very_good": 54.0279
        }
      }
    },
    "hh_size": {
      "perc": {
        "2011": {
          "five_people": 100,
          "four_people": 100,
          "one_person": 100,
          "three_people": 100,
          "two_people": 100
        },
        "2021": {
          "five_people": 9.5808,
          "four_people": 20.6587,
          "one_person": 14.6707,
          "three_people": 22.4551,
          "two_people": 32.6347
        }
      }
    },
    "highest_level_of_qualifications": {
      "perc": {
        "2011": {
          "apprenticeship": 100,
          "level_1_qualifications": 100,
          "level_2_qualifications": 100,
          "level_3_qualifications": 100,
          "level_4_qualifications_and_above": 100,
          "no_qualifications": 100,
          "other_qualifications": 100
        },
        "2021": {
          "apprenticeship": 6.2585,
          "level_1_qualifications": 5.5782,
          "level_2_qualifications": 18.7755,
          "level_3_qualifications": 19.1837,
          "level_4_qualifications_and_above": 32.517,
          "no_qualifications": 15.3741,
          "other_qualifications": 2.3129
        }
      }
    },
    "car_or_van": {
      "perc": {
        "2011": {
          "five_or_more": 100,
          "four": 100,
          "none": 100,
          "one": 100,
          "three": 100,
          "two": 100
        },
        "2021": {
          "five_or_more": 0.3003,
          "four": 2.4024,
          "none": 6.006,
          "one": 37.5375,
          "three": 10.8108,
          "two": 42.9429
        }
      }
    },
    "mainlang": {
      "perc": {
        "2011": {
          "english": 100,
          "other_languages": 100
        },
        "2021": {
          "english": 92,
          "other_languages": 8
        }
      }
    },
    "age": {
      "perc": {
        "2011": {
          "a0to14": 100,
          "a15to39": 100,
          "a40to64": 100,
          "a65plus": 100
        },
        "2021": {
          "a0to14": 20.0859,
          "a15to39": 30.7197,
          "a40to64": 36.8421,
          "a65plus": 12.3523
        }
      }
    },
    "provision_care": {
      "perc": {
        "2011": {
          "a1to19_hours": 100,
          "a20to49_hours": 100,
          "a50plus_hours": 100,
          "no_care": 100
        },
        "2021": {
          "a1to19_hours": 5.0905,
          "a20to49_hours": 3.2805,
          "a50plus_hours": 3.2805,
          "no_care": 88.3484
        }
      }
    },
    "religion_or_religion_brought_up_in": {
      "perc": {
        "2011": {
          "catholic": 100,
          "none": 100,
          "other_religions": 100,
          "protestant_and_other_christian_including_christian_related": 100
        },
        "2021": {
          "catholic": 38.0236,
          "none": 15.3598,
          "other_religions": 1.7186,
          "protestant_and_other_christian_including_christian_related": 44.898
        }
      }
    },
    "renewable_energy": {
      "perc": {
        "2011": {
          "any_renewable": 100,
          "no_renewable": 100
        },
        "2021": {
          "any_renewable": 3.6145,
          "no_renewable": 96.3855
        }
      }
    },
    "sex": {
      "perc": {
        "2011": {
          "females": 100,
          "males": 100
        },
        "2021": {
          "females": 50.1611,
          "males": 49.8389
        }
      }
    },
    "BS": {
      "value": {
        "IS": 0,
        "JSA": 0,
        "RP": 90,
        "PC": 10,
        "AA": 20,
        "CA": 10,
        "DLA": 30,
        "ESA": 30,
        "UC": 50,
        "PIP": 60
      }
    },
    "MYETotal": {
      "value": 931
    }
  },
  "hectares": 69,
  "meta_data": {
    "MYETotal": [
      {
        "table_code": "MYE01T011",
        "dataset_url": "https://data.nisra.gov.uk/table/MYE01T011",
        "geog_level": "dz",
        "last_updated": "2024-07-30",
        "email": "census@nisra.gov.uk",
        "title": "Mid-year population estimates",
        "year": "2022"
      }
    ],
    "BS": [
      {
        "table_code": "BSDZ",
        "dataset_url": "https://data.nisra.gov.uk/table/BSDZ",
        "geog_level": "dz",
        "last_updated": "2024-09-24",
        "email": "analyticsdivision@communities-ni.gov.uk",
        "title": "Benefit Statistics",
        "year": "2024"
      }
    ]
  }
}
