{
  "code": "N20001856",
  "name": "Waterside_B3",
  "comment": "This JSON includes data for the area explorer app.",
  "type": "dz",
  "count": 3780,
  "parents": [
    {
      "code": "N21000424",
      "name": "Waterside_B",
      "type": "sdz"
    },
    {
      "code": "N10000507",
      "name": "Waterside",
      "type": "dea"
    },
    {
      "code": "N09000005",
      "name": "Derry City and Strabane",
      "type": "lgd"
    },
    {
      "code": "N92000002",
      "name": "Northern Ireland",
      "type": "ctry"
    }
  ],
  "children": [],
  "bounds": [
    [-7.2774, 54.9999],
    [-7.2859, 55.0049]
  ],
  "data": {
    "population": {
      "perc": {
        "2011": {
          "all": 100
        },
        "2021": {
          "all": 100
        }
      },
      "value": {
        "2011": {
          "all": 0
        },
        "change": {
          "all": "Inf"
        },
        "2021": {
          "all": 511
        }
      },
      "value_rank": {
        "2011": {
          "all": 0
        },
        "2021": {
          "all": 1689
        }
      }
    },
    "households": {
      "perc": {
        "2011": {
          "all_households": 100
        },
        "2021": {
          "all_households": 100
        }
      },
      "value": {
        "2011": {
          "all_households": 0
        },
        "change": {
          "all_households": "Inf"
        },
        "2021": {
          "all_households": 240
        }
      }
    },
    "cob": {
      "perc": {
        "2011": {
          "england": 100,
          "northern_ireland": 100,
          "other_cob": 100,
          "republic_of_ireland": 100,
          "scotland": 100,
          "wales": 100
        },
        "2021": {
          "england": 6.0665,
          "northern_ireland": 87.6712,
          "other_cob": 2.7397,
          "republic_of_ireland": 1.5656,
          "scotland": 1.9569,
          "wales": 0
        }
      }
    },
    "general_health": {
      "perc": {
        "2011": {
          "bad": 100,
          "fair": 100,
          "good": 100,
          "very_bad": 100,
          "very_good": 100
        },
        "2021": {
          "bad": 11.9374,
          "fair": 18.591,
          "good": 26.8102,
          "very_bad": 3.3268,
          "very_good": 39.3346
        }
      }
    },
    "hh_size": {
      "perc": {
        "2011": {
          "five_people": 100,
          "four_people": 100,
          "one_person": 100,
          "three_people": 100,
          "two_people": 100
        },
        "2021": {
          "five_people": 4.1667,
          "four_people": 10,
          "one_person": 38.75,
          "three_people": 15.4167,
          "two_people": 31.6667
        }
      }
    },
    "highest_level_of_qualifications": {
      "perc": {
        "2011": {
          "apprenticeship": 100,
          "level_1_qualifications": 100,
          "level_2_qualifications": 100,
          "level_3_qualifications": 100,
          "level_4_qualifications_and_above": 100,
          "no_qualifications": 100,
          "other_qualifications": 100
        },
        "2021": {
          "apprenticeship": 3.599,
          "level_1_qualifications": 8.7404,
          "level_2_qualifications": 12.3393,
          "level_3_qualifications": 15.6812,
          "level_4_qualifications_and_above": 16.4524,
          "no_qualifications": 42.1594,
          "other_qualifications": 1.0283
        }
      }
    },
    "car_or_van": {
      "perc": {
        "2011": {
          "five_or_more": 100,
          "four": 100,
          "none": 100,
          "one": 100,
          "three": 100,
          "two": 100
        },
        "2021": {
          "five_or_more": 0,
          "four": 0.4167,
          "none": 39.1667,
          "one": 50.4167,
          "three": 2.5,
          "two": 7.5
        }
      }
    },
    "mainlang": {
      "perc": {
        "2011": {
          "english": 100,
          "other_languages": 100
        },
        "2021": {
          "english": 98.5685,
          "other_languages": 1.4315
        }
      }
    },
    "age": {
      "perc": {
        "2011": {
          "a0to14": 100,
          "a15to39": 100,
          "a40to64": 100,
          "a65plus": 100
        },
        "2021": {
          "a0to14": 23.2877,
          "a15to39": 32.0939,
          "a40to64": 27.9843,
          "a65plus": 16.6341
        }
      }
    },
    "provision_care": {
      "perc": {
        "2011": {
          "a1to19_hours": 100,
          "a20to49_hours": 100,
          "a50plus_hours": 100,
          "no_care": 100
        },
        "2021": {
          "a1to19_hours": 4.2373,
          "a20to49_hours": 4.0254,
          "a50plus_hours": 4.4492,
          "no_care": 87.2881
        }
      }
    },
    "religion_or_religion_brought_up_in": {
      "perc": {
        "2011": {
          "catholic": 100,
          "none": 100,
          "other_religions": 100,
          "protestant_and_other_christian_including_christian_related": 100
        },
        "2021": {
          "catholic": 7.045,
          "none": 8.0235,
          "other_religions": 0,
          "protestant_and_other_christian_including_christian_related": 84.9315
        }
      }
    },
    "renewable_energy": {
      "perc": {
        "2011": {
          "any_renewable": 100,
          "no_renewable": 100
        },
        "2021": {
          "any_renewable": 2.0833,
          "no_renewable": 97.9167
        }
      }
    },
    "sex": {
      "perc": {
        "2011": {
          "females": 100,
          "males": 100
        },
        "2021": {
          "females": 56.1644,
          "males": 43.8356
        }
      }
    },
    "BS": {
      "value": {
        "IS": 10,
        "JSA": 0,
        "RP": 70,
        "PC": 20,
        "AA": 10,
        "CA": 30,
        "DLA": 40,
        "ESA": 40,
        "UC": 100,
        "PIP": 90
      }
    },
    "MYETotal": {
      "value": 491
    }
  },
  "hectares": 15,
  "meta_data": {
    "MYETotal": [
      {
        "table_code": "MYE01T011",
        "dataset_url": "https://data.nisra.gov.uk/table/MYE01T011",
        "geog_level": "dz",
        "last_updated": "2024-07-30",
        "email": "census@nisra.gov.uk",
        "title": "Mid-year population estimates",
        "year": "2022"
      }
    ],
    "BS": [
      {
        "table_code": "BSDZ",
        "dataset_url": "https://data.nisra.gov.uk/table/BSDZ",
        "geog_level": "dz",
        "last_updated": "2024-09-24",
        "email": "analyticsdivision@communities-ni.gov.uk",
        "title": "Benefit Statistics",
        "year": "2024"
      }
    ]
  }
}
