{
  "code": "N20000691",
  "name": "Cusher_G4",
  "comment": "This JSON includes data for the area explorer app.",
  "type": "dz",
  "count": 3780,
  "parents": [
    {
      "code": "N21000156",
      "name": "Cusher_G",
      "type": "sdz"
    },
    {
      "code": "N10000204",
      "name": "Cusher",
      "type": "dea"
    },
    {
      "code": "N09000002",
      "name": "Armagh City, Banbridge and Craigavon",
      "type": "lgd"
    },
    {
      "code": "N92000002",
      "name": "Northern Ireland",
      "type": "ctry"
    }
  ],
  "children": [],
  "bounds": [
    [-6.4543, 54.2955],
    [-6.5296, 54.3444]
  ],
  "data": {
    "population": {
      "perc": {
        "2011": {
          "all": 100
        },
        "2021": {
          "all": 100
        }
      },
      "value": {
        "2011": {
          "all": 0
        },
        "change": {
          "all": "Inf"
        },
        "2021": {
          "all": 534
        }
      },
      "value_rank": {
        "2011": {
          "all": 0
        },
        "2021": {
          "all": 1460
        }
      }
    },
    "households": {
      "perc": {
        "2011": {
          "all_households": 100
        },
        "2021": {
          "all_households": 100
        }
      },
      "value": {
        "2011": {
          "all_households": 0
        },
        "change": {
          "all_households": "Inf"
        },
        "2021": {
          "all_households": 205
        }
      }
    },
    "cob": {
      "perc": {
        "2011": {
          "england": 100,
          "northern_ireland": 100,
          "other_cob": 100,
          "republic_of_ireland": 100,
          "scotland": 100,
          "wales": 100
        },
        "2021": {
          "england": 3.3708,
          "northern_ireland": 91.0112,
          "other_cob": 2.0599,
          "republic_of_ireland": 2.0599,
          "scotland": 0.7491,
          "wales": 0.7491
        }
      }
    },
    "general_health": {
      "perc": {
        "2011": {
          "bad": 100,
          "fair": 100,
          "good": 100,
          "very_bad": 100,
          "very_good": 100
        },
        "2021": {
          "bad": 3.5581,
          "fair": 13.6704,
          "good": 28.2772,
          "very_bad": 1.4981,
          "very_good": 52.9963
        }
      }
    },
    "hh_size": {
      "perc": {
        "2011": {
          "five_people": 100,
          "four_people": 100,
          "one_person": 100,
          "three_people": 100,
          "two_people": 100
        },
        "2021": {
          "five_people": 10.2439,
          "four_people": 18.5366,
          "one_person": 22.439,
          "three_people": 12.6829,
          "two_people": 36.0976
        }
      }
    },
    "highest_level_of_qualifications": {
      "perc": {
        "2011": {
          "apprenticeship": 100,
          "level_1_qualifications": 100,
          "level_2_qualifications": 100,
          "level_3_qualifications": 100,
          "level_4_qualifications_and_above": 100,
          "no_qualifications": 100,
          "other_qualifications": 100
        },
        "2021": {
          "apprenticeship": 6.982,
          "level_1_qualifications": 4.2793,
          "level_2_qualifications": 12.8378,
          "level_3_qualifications": 18.6937,
          "level_4_qualifications_and_above": 34.009,
          "no_qualifications": 20.9459,
          "other_qualifications": 2.2523
        }
      }
    },
    "car_or_van": {
      "perc": {
        "2011": {
          "five_or_more": 100,
          "four": 100,
          "none": 100,
          "one": 100,
          "three": 100,
          "two": 100
        },
        "2021": {
          "five_or_more": 4.8309,
          "four": 4.3478,
          "none": 6.2802,
          "one": 28.0193,
          "three": 16.4251,
          "two": 40.0966
        }
      }
    },
    "mainlang": {
      "perc": {
        "2011": {
          "english": 100,
          "other_languages": 100
        },
        "2021": {
          "english": 99.0329,
          "other_languages": 0.9671
        }
      }
    },
    "age": {
      "perc": {
        "2011": {
          "a0to14": 100,
          "a15to39": 100,
          "a40to64": 100,
          "a65plus": 100
        },
        "2021": {
          "a0to14": 15.6134,
          "a15to39": 26.9517,
          "a40to64": 35.316,
          "a65plus": 22.119
        }
      }
    },
    "provision_care": {
      "perc": {
        "2011": {
          "a1to19_hours": 100,
          "a20to49_hours": 100,
          "a50plus_hours": 100,
          "no_care": 100
        },
        "2021": {
          "a1to19_hours": 9.6457,
          "a20to49_hours": 2.9528,
          "a50plus_hours": 3.5433,
          "no_care": 83.8583
        }
      }
    },
    "religion_or_religion_brought_up_in": {
      "perc": {
        "2011": {
          "catholic": 100,
          "none": 100,
          "other_religions": 100,
          "protestant_and_other_christian_including_christian_related": 100
        },
        "2021": {
          "catholic": 6.1798,
          "none": 8.2397,
          "other_religions": 0.7491,
          "protestant_and_other_christian_including_christian_related": 84.8315
        }
      }
    },
    "renewable_energy": {
      "perc": {
        "2011": {
          "any_renewable": 100,
          "no_renewable": 100
        },
        "2021": {
          "any_renewable": 11.7073,
          "no_renewable": 88.2927
        }
      }
    },
    "sex": {
      "perc": {
        "2011": {
          "females": 100,
          "males": 100
        },
        "2021": {
          "females": 50.9363,
          "males": 49.0637
        }
      }
    },
    "BS": {
      "value": {
        "IS": 0,
        "JSA": 0,
        "RP": 100,
        "PC": 10,
        "AA": 10,
        "CA": 20,
        "DLA": 20,
        "ESA": 20,
        "UC": 10,
        "PIP": 30
      }
    },
    "MYETotal": {
      "value": 533
    }
  },
  "hectares": 1373,
  "meta_data": {
    "MYETotal": [
      {
        "table_code": "MYE01T011",
        "dataset_url": "https://data.nisra.gov.uk/table/MYE01T011",
        "geog_level": "dz",
        "last_updated": "2024-07-30",
        "email": "census@nisra.gov.uk",
        "title": "Mid-year population estimates",
        "year": "2022"
      }
    ],
    "BS": [
      {
        "table_code": "BSDZ",
        "dataset_url": "https://data.nisra.gov.uk/table/BSDZ",
        "geog_level": "dz",
        "last_updated": "2023-07-06",
        "email": "psu@communities-ni.gov.uk",
        "title": "Benefit Statistics",
        "year": "2023"
      }
    ]
  }
}
