{
  "code": "N20000870",
  "name": "Titanic_F1",
  "comment": "This JSON includes data for the area explorer app.",
  "type": "dz",
  "count": 3780,
  "parents": [
    {
      "code": "N21000202",
      "name": "Titanic_F",
      "type": "sdz"
    },
    {
      "code": "N10000310",
      "name": "Titanic",
      "type": "dea"
    },
    {
      "code": "N09000003",
      "name": "Belfast",
      "type": "lgd"
    },
    {
      "code": "N92000002",
      "name": "Northern Ireland",
      "type": "ctry"
    }
  ],
  "children": [],
  "bounds": [
    [-5.8912, 54.6014],
    [-5.8987, 54.6035]
  ],
  "data": {
    "population": {
      "perc": {
        "2011": {
          "all": 100
        },
        "2021": {
          "all": 100
        }
      },
      "value": {
        "2011": {
          "all": 0
        },
        "change": {
          "all": "Inf"
        },
        "2021": {
          "all": 407
        }
      },
      "value_rank": {
        "2011": {
          "all": 0
        },
        "2021": {
          "all": 2797
        }
      }
    },
    "households": {
      "perc": {
        "2011": {
          "all_households": 100
        },
        "2021": {
          "all_households": 100
        }
      },
      "value": {
        "2011": {
          "all_households": 0
        },
        "change": {
          "all_households": "Inf"
        },
        "2021": {
          "all_households": 197
        }
      }
    },
    "cob": {
      "perc": {
        "2011": {
          "england": 100,
          "northern_ireland": 100,
          "other_cob": 100,
          "republic_of_ireland": 100,
          "scotland": 100,
          "wales": 100
        },
        "2021": {
          "england": 2.9484,
          "northern_ireland": 89.9263,
          "other_cob": 5.8968,
          "republic_of_ireland": 0,
          "scotland": 1.2285,
          "wales": 0
        }
      }
    },
    "general_health": {
      "perc": {
        "2011": {
          "bad": 100,
          "fair": 100,
          "good": 100,
          "very_bad": 100,
          "very_good": 100
        },
        "2021": {
          "bad": 14.0049,
          "fair": 22.8501,
          "good": 24.57,
          "very_bad": 4.914,
          "very_good": 33.6609
        }
      }
    },
    "hh_size": {
      "perc": {
        "2011": {
          "five_people": 100,
          "four_people": 100,
          "one_person": 100,
          "three_people": 100,
          "two_people": 100
        },
        "2021": {
          "five_people": 5.5838,
          "four_people": 11.1675,
          "one_person": 48.2234,
          "three_people": 12.6904,
          "two_people": 22.335
        }
      }
    },
    "highest_level_of_qualifications": {
      "perc": {
        "2011": {
          "apprenticeship": 100,
          "level_1_qualifications": 100,
          "level_2_qualifications": 100,
          "level_3_qualifications": 100,
          "level_4_qualifications_and_above": 100,
          "no_qualifications": 100,
          "other_qualifications": 100
        },
        "2021": {
          "apprenticeship": 5.1282,
          "level_1_qualifications": 5.7692,
          "level_2_qualifications": 13.4615,
          "level_3_qualifications": 12.5,
          "level_4_qualifications_and_above": 11.859,
          "no_qualifications": 47.4359,
          "other_qualifications": 3.8462
        }
      }
    },
    "car_or_van": {
      "perc": {
        "2011": {
          "five_or_more": 100,
          "four": 100,
          "none": 100,
          "one": 100,
          "three": 100,
          "two": 100
        },
        "2021": {
          "five_or_more": 0,
          "four": 0,
          "none": 50.2538,
          "one": 38.0711,
          "three": 2.5381,
          "two": 9.1371
        }
      }
    },
    "mainlang": {
      "perc": {
        "2011": {
          "english": 100,
          "other_languages": 100
        },
        "2021": {
          "english": 95.99,
          "other_languages": 4.01
        }
      }
    },
    "age": {
      "perc": {
        "2011": {
          "a0to14": 100,
          "a15to39": 100,
          "a40to64": 100,
          "a65plus": 100
        },
        "2021": {
          "a0to14": 21.5686,
          "a15to39": 26.7157,
          "a40to64": 35.2941,
          "a65plus": 16.4216
        }
      }
    },
    "provision_care": {
      "perc": {
        "2011": {
          "a1to19_hours": 100,
          "a20to49_hours": 100,
          "a50plus_hours": 100,
          "no_care": 100
        },
        "2021": {
          "a1to19_hours": 4.6154,
          "a20to49_hours": 5.8974,
          "a50plus_hours": 4.8718,
          "no_care": 84.6154
        }
      }
    },
    "religion_or_religion_brought_up_in": {
      "perc": {
        "2011": {
          "catholic": 100,
          "none": 100,
          "other_religions": 100,
          "protestant_and_other_christian_including_christian_related": 100
        },
        "2021": {
          "catholic": 7.371,
          "none": 17.6904,
          "other_religions": 0.7371,
          "protestant_and_other_christian_including_christian_related": 74.2015
        }
      }
    },
    "renewable_energy": {
      "perc": {
        "2011": {
          "any_renewable": 100,
          "no_renewable": 100
        },
        "2021": {
          "any_renewable": 9.1371,
          "no_renewable": 90.8629
        }
      }
    },
    "sex": {
      "perc": {
        "2011": {
          "females": 100,
          "males": 100
        },
        "2021": {
          "females": 48.1572,
          "males": 51.8428
        }
      }
    },
    "BS": {
      "value": {
        "IS": 10,
        "JSA": 0,
        "RP": 70,
        "PC": 30,
        "AA": 20,
        "CA": 40,
        "DLA": 40,
        "ESA": 60,
        "UC": 100,
        "PIP": 110
      }
    },
    "MYETotal": {
      "value": 422
    }
  },
  "hectares": 7,
  "meta_data": {
    "MYETotal": [
      {
        "table_code": "MYE01T011",
        "dataset_url": "https://data.nisra.gov.uk/table/MYE01T011",
        "geog_level": "dz",
        "last_updated": "2024-07-30",
        "email": "census@nisra.gov.uk",
        "title": "Mid-year population estimates",
        "year": "2022"
      }
    ],
    "BS": [
      {
        "table_code": "BSDZ",
        "dataset_url": "https://data.nisra.gov.uk/table/BSDZ",
        "geog_level": "dz",
        "last_updated": "2023-07-06",
        "email": "psu@communities-ni.gov.uk",
        "title": "Benefit Statistics",
        "year": "2023"
      }
    ]
  }
}
